{
	"song": {
		"player1": "michu-left",
		"player2": "aquino-left",
		"notes": [
			{
				"lengthInSteps": 16,
				"sectionNotes": [],
				"mustHitSection": false
			},
			{
				"lengthInSteps": 16,
				"sectionNotes": [],
				"mustHitSection": false
			},
			{
				"lengthInSteps": 16,
				"sectionNotes": [],
				"mustHitSection": true
			},
			{
				"lengthInSteps": 16,
				"sectionNotes": [],
				"mustHitSection": true
			},
			{
				"lengthInSteps": 16,
				"sectionNotes": [],
				"mustHitSection": false
			},
			{
				"lengthInSteps": 16,
				"sectionNotes": [],
				"mustHitSection": false
			},
			{
				"lengthInSteps": 16,
				"sectionNotes": [],
				"mustHitSection": true
			},
			{
				"lengthInSteps": 16,
				"sectionNotes": [],
				"mustHitSection": true
			},
			{
				"lengthInSteps": 16,
				"sectionNotes": [
					[
						15360,
						0,
						120
					],
					[
						15600,
						1,
						0
					],
					[
						15720,
						3,
						0
					],
					[
						15840,
						1,
						120
					],
					[
						16080,
						2,
						120
					],
					[
						16320,
						0,
						0
					],
					[
						16440,
						2,
						0
					],
					[
						16560,
						3,
						0
					],
					[
						16620,
						1,
						0
					],
					[
						16680,
						2,
						0
					],
					[
						16800,
						0,
						0
					],
					[
						16920,
						3,
						0
					],
					[
						17040,
						2,
						0
					],
					[
						17160,
						1,
						0
					]
				],
				"mustHitSection": true
			},
			{
				"lengthInSteps": 16,
				"sectionNotes": [
					[
						17280,
						0,
						0
					],
					[
						17520,
						3,
						0
					],
					[
						17340,
						1,
						60
					],
					[
						17640,
						2,
						0
					],
					[
						17700,
						0,
						60
					],
					[
						17880,
						1,
						0
					],
					[
						18000,
						3,
						120
					],
					[
						18240,
						2,
						0
					],
					[
						18360,
						0,
						0
					],
					[
						18480,
						2,
						0
					],
					[
						18600,
						1,
						0
					],
					[
						18720,
						3,
						0
					],
					[
						18840,
						2,
						0
					],
					[
						18960,
						0,
						0
					],
					[
						19080,
						1,
						0
					]
				],
				"mustHitSection": true
			},
			{
				"gfSection": true,
				"lengthInSteps": 16,
				"sectionNotes": [
					[
						19200,
						3,
						0
					],
					[
						19440,
						2,
						0
					],
					[
						19260,
						1,
						60
					],
					[
						19560,
						0,
						0
					],
					[
						19620,
						3,
						0
					],
					[
						19800,
						2,
						0
					],
					[
						19920,
						1,
						120
					],
					[
						20160,
						0,
						0
					],
					[
						20280,
						2,
						0
					],
					[
						20340,
						1,
						0
					],
					[
						20400,
						3,
						0
					],
					[
						20520,
						2,
						0
					],
					[
						20640,
						0,
						0
					],
					[
						20760,
						2,
						0
					],
					[
						20880,
						1,
						120
					]
				],
				"mustHitSection": true
			},
			{
				"gfSection": true,
				"lengthInSteps": 16,
				"sectionNotes": [
					[
						21120,
						3,
						0
					],
					[
						21180,
						1,
						0
					],
					[
						21240,
						3,
						0
					],
					[
						21300,
						1,
						0
					],
					[
						21360,
						0,
						0
					],
					[
						21480,
						1,
						0
					],
					[
						21600,
						3,
						0
					],
					[
						21720,
						2,
						0
					],
					[
						21840,
						0,
						0
					],
					[
						21960,
						1,
						0
					],
					[
						22080,
						3,
						60
					],
					[
						22320,
						2,
						60
					],
					[
						22560,
						0,
						60
					],
					[
						22800,
						1,
						60
					]
				],
				"mustHitSection": true
			},
			{
				"gfSection": false,
				"lengthInSteps": 16,
				"sectionNotes": [
					[
						23040,
						1,
						120
					],
					[
						23280,
						0,
						0
					],
					[
						23400,
						2,
						0
					],
					[
						23520,
						1,
						120
					],
					[
						23760,
						3,
						120
					],
					[
						24000,
						2,
						0
					],
					[
						24120,
						0,
						0
					],
					[
						24240,
						2,
						0
					],
					[
						24300,
						3,
						0
					],
					[
						24360,
						2,
						0
					],
					[
						24480,
						0,
						0
					],
					[
						24600,
						1,
						0
					],
					[
						24720,
						3,
						0
					],
					[
						24840,
						2,
						0
					]
				],
				"mustHitSection": false
			},
			{
				"lengthInSteps": 16,
				"sectionNotes": [
					[
						24960,
						0,
						0
					],
					[
						25020,
						1,
						0
					],
					[
						25200,
						3,
						0
					],
					[
						25320,
						2,
						0
					],
					[
						25380,
						0,
						60
					],
					[
						25560,
						1,
						0
					],
					[
						25680,
						3,
						120
					],
					[
						25920,
						2,
						0
					],
					[
						26040,
						0,
						0
					],
					[
						26160,
						2,
						0
					],
					[
						26280,
						1,
						0
					],
					[
						26400,
						3,
						0
					],
					[
						26520,
						1,
						0
					],
					[
						26640,
						2,
						0
					],
					[
						26760,
						0,
						0
					]
				],
				"mustHitSection": false
			},
			{
				"lengthInSteps": 16,
				"sectionNotes": [
					[
						26880,
						3,
						0,
						"Enemyextra1"
					],
					[
						27120,
						2,
						0,
						"Enemyextra1"
					],
					[
						26940,
						1,
						60,
						"Enemyextra1"
					],
					[
						27240,
						0,
						120,
						"Enemyextra1"
					],
					[
						27480,
						2,
						0,
						"Enemyextra1"
					],
					[
						27600,
						1,
						120,
						"Enemyextra1"
					],
					[
						27840,
						3,
						0,
						"Enemyextra1"
					],
					[
						27960,
						1,
						0,
						"Enemyextra1"
					],
					[
						28020,
						0,
						0,
						"Enemyextra1"
					],
					[
						28080,
						2,
						0,
						"Enemyextra1"
					],
					[
						28200,
						1,
						0,
						"Enemyextra1"
					],
					[
						28320,
						3,
						0,
						"Enemyextra1"
					],
					[
						28440,
						2,
						0,
						"Enemyextra1"
					],
					[
						28560,
						0,
						120,
						"Enemyextra1"
					]
				],
				"mustHitSection": false
			},
			{
				"lengthInSteps": 16,
				"sectionNotes": [
					[
						28800,
						1,
						0,
						"Enemyextra1"
					],
					[
						28860,
						3,
						0,
						"Enemyextra1"
					],
					[
						28920,
						1,
						0,
						"Enemyextra1"
					],
					[
						28980,
						2,
						0,
						"Enemyextra1"
					],
					[
						29040,
						0,
						0,
						"Enemyextra1"
					],
					[
						29160,
						1,
						0,
						"Enemyextra1"
					],
					[
						29280,
						3,
						0,
						"Enemyextra1"
					],
					[
						29400,
						2,
						0,
						"Enemyextra1"
					],
					[
						29520,
						0,
						0,
						"Enemyextra1"
					],
					[
						29640,
						1,
						0,
						"Enemyextra1"
					],
					[
						29760,
						3,
						120,
						"Enemyextra1"
					],
					[
						29760,
						2,
						0,
						"Enemyextra1"
					],
					[
						30000,
						2,
						60,
						"Enemyextra1"
					],
					[
						30240,
						0,
						60,
						"Enemyextra1"
					],
					[
						30480,
						3,
						60,
						"Enemyextra1"
					]
				],
				"mustHitSection": false
			},
			{
				"gfSection": false,
				"lengthInSteps": 16,
				"sectionNotes": [
					[
						30720,
						1,
						60,
						"Enemyextra1"
					],
					[
						30720,
						3,
						60
					],
					[
						30960,
						1,
						0
					],
					[
						31080,
						0,
						0
					],
					[
						31200,
						2,
						0
					],
					[
						31320,
						1,
						0
					],
					[
						31440,
						3,
						120
					],
					[
						31680,
						1,
						0
					],
					[
						31800,
						2,
						0
					],
					[
						31920,
						0,
						0
					],
					[
						32040,
						1,
						0
					],
					[
						32160,
						3,
						360
					]
				],
				"mustHitSection": false
			},
			{
				"gfSection": false,
				"lengthInSteps": 16,
				"sectionNotes": [
					[
						32640,
						1,
						60
					],
					[
						32640,
						0,
						60,
						"Enemyextra1"
					],
					[
						32880,
						1,
						0,
						"Enemyextra1"
					],
					[
						33000,
						2,
						0,
						"Enemyextra1"
					],
					[
						33120,
						1,
						0,
						"Enemyextra1"
					],
					[
						33240,
						3,
						0,
						"Enemyextra1"
					],
					[
						33360,
						1,
						120,
						"Enemyextra1"
					],
					[
						33600,
						0,
						0,
						"Enemyextra1"
					],
					[
						33720,
						1,
						0,
						"Enemyextra1"
					],
					[
						33840,
						3,
						0,
						"Enemyextra1"
					],
					[
						33960,
						2,
						0,
						"Enemyextra1"
					],
					[
						34080,
						0,
						60,
						"Enemyextra1"
					],
					[
						34320,
						1,
						60,
						"Enemyextra1"
					]
				],
				"mustHitSection": false
			},
			{
				"gfSection": false,
				"lengthInSteps": 16,
				"sectionNotes": [
					[
						34560,
						3,
						0,
						"Enemyextra1"
					],
					[
						34680,
						2,
						0,
						"Enemyextra1"
					],
					[
						34800,
						0,
						120,
						"Enemyextra1"
					],
					[
						35040,
						1,
						0,
						"Enemyextra1"
					],
					[
						35160,
						3,
						0,
						"Enemyextra1"
					],
					[
						35280,
						2,
						120,
						"Enemyextra1"
					],
					[
						35520,
						0,
						0,
						"Enemyextra1"
					],
					[
						35640,
						2,
						0,
						"Enemyextra1"
					],
					[
						35760,
						1,
						0,
						"Enemyextra1"
					],
					[
						35880,
						3,
						0,
						"Enemyextra1"
					],
					[
						36000,
						1,
						0,
						"Enemyextra1"
					],
					[
						36120,
						0,
						0,
						"Enemyextra1"
					],
					[
						36240,
						1,
						120,
						"Enemyextra1"
					]
				],
				"mustHitSection": false
			},
			{
				"lengthInSteps": 16,
				"sectionNotes": [
					[
						36480,
						0,
						120
					],
					[
						36720,
						1,
						0
					],
					[
						36840,
						3,
						0
					],
					[
						36960,
						1,
						0
					],
					[
						37080,
						2,
						0
					],
					[
						37200,
						0,
						120
					],
					[
						37440,
						2,
						0
					],
					[
						37560,
						1,
						0
					],
					[
						37680,
						3,
						0
					],
					[
						37800,
						1,
						0
					],
					[
						37920,
						0,
						0
					],
					[
						38040,
						2,
						0
					],
					[
						38160,
						1,
						0
					],
					[
						38280,
						3,
						0
					]
				],
				"mustHitSection": false
			},
			{
				"lengthInSteps": 16,
				"sectionNotes": [
					[
						38400,
						5,
						240
					],
					[
						38400,
						1,
						0
					],
					[
						38640,
						2,
						0
					],
					[
						38760,
						1,
						0
					],
					[
						38880,
						3,
						0
					],
					[
						39000,
						1,
						0
					],
					[
						39120,
						0,
						120
					],
					[
						39360,
						1,
						0
					],
					[
						39480,
						3,
						0
					],
					[
						39600,
						2,
						0
					],
					[
						39720,
						0,
						0
					],
					[
						39840,
						2,
						360
					]
				],
				"mustHitSection": true
			},
			{
				"gfSection": true,
				"lengthInSteps": 16,
				"sectionNotes": [
					[
						40320,
						0,
						60
					],
					[
						40560,
						1,
						0
					],
					[
						40680,
						3,
						0
					],
					[
						40800,
						1,
						0
					],
					[
						40920,
						2,
						0
					],
					[
						41040,
						0,
						120
					],
					[
						41280,
						2,
						0
					],
					[
						41400,
						1,
						0
					],
					[
						41520,
						3,
						0
					],
					[
						41640,
						2,
						0
					],
					[
						42000,
						1,
						120
					],
					[
						41760,
						0,
						120
					]
				],
				"mustHitSection": true
			},
			{
				"gfSection": true,
				"lengthInSteps": 16,
				"sectionNotes": [
					[
						42240,
						3,
						0
					],
					[
						42360,
						1,
						0
					],
					[
						42480,
						0,
						120
					],
					[
						42720,
						2,
						0
					],
					[
						42840,
						3,
						0
					],
					[
						42960,
						2,
						120
					],
					[
						43200,
						1,
						0
					],
					[
						43320,
						0,
						0
					],
					[
						43440,
						2,
						0
					],
					[
						43560,
						1,
						0
					],
					[
						43680,
						3,
						0
					],
					[
						43800,
						1,
						0
					],
					[
						43920,
						0,
						120
					]
				],
				"mustHitSection": true
			},
			{
				"lengthInSteps": 16,
				"sectionNotes": [
					[
						44160,
						1,
						120
					],
					[
						44400,
						3,
						0
					],
					[
						44520,
						1,
						0
					],
					[
						44640,
						2,
						0
					],
					[
						44760,
						0,
						0
					],
					[
						44880,
						2,
						120
					],
					[
						44880,
						3,
						0
					],
					[
						45120,
						1,
						0
					],
					[
						45240,
						3,
						0
					],
					[
						45360,
						2,
						0
					],
					[
						45480,
						1,
						0
					],
					[
						45600,
						0,
						0
					],
					[
						45720,
						2,
						0
					],
					[
						45840,
						3,
						0
					],
					[
						45960,
						0,
						0
					]
				],
				"mustHitSection": true
			},
			{
				"gfSection": true,
				"lengthInSteps": 16,
				"sectionNotes": [
					[
						46080,
						1,
						120
					],
					[
						46320,
						3,
						0
					],
					[
						46440,
						1,
						0
					],
					[
						46560,
						2,
						120
					],
					[
						46800,
						0,
						0
					],
					[
						47040,
						2,
						0
					],
					[
						47160,
						1,
						0
					],
					[
						47280,
						3,
						0
					],
					[
						47400,
						1,
						0
					],
					[
						47520,
						0,
						300
					]
				],
				"mustHitSection": true
			},
			{
				"lengthInSteps": 16,
				"sectionNotes": [
					[
						48000,
						1,
						60
					],
					[
						48240,
						0,
						0
					],
					[
						48360,
						2,
						0
					],
					[
						48480,
						1,
						120
					],
					[
						48720,
						3,
						120
					],
					[
						48960,
						2,
						0
					],
					[
						49080,
						0,
						0
					],
					[
						49200,
						2,
						0
					],
					[
						49320,
						1,
						0
					],
					[
						49440,
						3,
						120
					],
					[
						49680,
						1,
						120
					]
				],
				"mustHitSection": false
			},
			{
				"lengthInSteps": 16,
				"sectionNotes": [
					[
						49920,
						0,
						120,
						"Enemyextra1"
					],
					[
						50160,
						1,
						0,
						"Enemyextra1"
					],
					[
						50280,
						3,
						0,
						"Enemyextra1"
					],
					[
						50400,
						1,
						120,
						"Enemyextra1"
					],
					[
						50640,
						2,
						0,
						"Enemyextra1"
					],
					[
						50760,
						0,
						120,
						"Enemyextra1"
					],
					[
						51000,
						2,
						0,
						"Enemyextra1"
					],
					[
						51120,
						1,
						0,
						"Enemyextra1"
					],
					[
						51240,
						3,
						0,
						"Enemyextra1"
					],
					[
						51360,
						2,
						0,
						"Enemyextra1"
					],
					[
						51480,
						0,
						0,
						"Enemyextra1"
					],
					[
						51600,
						1,
						120,
						"Enemyextra1"
					]
				],
				"mustHitSection": false
			},
			{
				"lengthInSteps": 16,
				"sectionNotes": [
					[
						51840,
						1,
						120
					],
					[
						52080,
						3,
						0
					],
					[
						52200,
						2,
						0
					],
					[
						52320,
						0,
						120
					],
					[
						52560,
						2,
						0
					],
					[
						52680,
						1,
						120
					],
					[
						52920,
						3,
						0
					],
					[
						53040,
						1,
						0
					],
					[
						53160,
						2,
						0
					],
					[
						53280,
						0,
						0
					],
					[
						53400,
						2,
						0
					],
					[
						53520,
						1,
						120
					]
				],
				"mustHitSection": true
			},
			{
				"lengthInSteps": 16,
				"sectionNotes": [
					[
						53760,
						3,
						120
					],
					[
						54000,
						1,
						0
					],
					[
						54120,
						2,
						0
					],
					[
						54240,
						0,
						120
					],
					[
						54480,
						1,
						120
					],
					[
						54720,
						3,
						0
					],
					[
						54780,
						2,
						0
					],
					[
						54840,
						0,
						0
					],
					[
						54960,
						1,
						0
					],
					[
						55080,
						3,
						0
					],
					[
						55200,
						1,
						0
					],
					[
						55320,
						2,
						0
					],
					[
						55440,
						0,
						120
					]
				],
				"mustHitSection": false
			},
			{
				"lengthInSteps": 16,
				"sectionNotes": [
					[
						55680,
						1,
						120,
						"Enemyextra1"
					],
					[
						55920,
						3,
						0,
						"Enemyextra1"
					],
					[
						56040,
						1,
						0,
						"Enemyextra1"
					],
					[
						56160,
						2,
						0,
						"Enemyextra1"
					],
					[
						56280,
						0,
						0,
						"Enemyextra1"
					],
					[
						56400,
						2,
						0,
						"Enemyextra1"
					],
					[
						56520,
						1,
						0,
						"Enemyextra1"
					],
					[
						56640,
						3,
						120,
						"Enemyextra1"
					],
					[
						56880,
						1,
						0,
						"Enemyextra1"
					],
					[
						57000,
						3,
						0,
						"Enemyextra1"
					],
					[
						57120,
						1,
						120,
						"Enemyextra1"
					],
					[
						57360,
						0,
						120,
						"Enemyextra1"
					]
				],
				"mustHitSection": false
			},
			{
				"lengthInSteps": 16,
				"sectionNotes": [
					[
						57600,
						1,
						120
					],
					[
						57840,
						3,
						0
					],
					[
						57960,
						1,
						0
					],
					[
						58080,
						2,
						120
					],
					[
						58320,
						0,
						120
					],
					[
						58560,
						2,
						0
					],
					[
						58620,
						1,
						0
					],
					[
						58680,
						3,
						0
					],
					[
						58800,
						1,
						0
					],
					[
						58920,
						2,
						0
					],
					[
						59040,
						0,
						0
					],
					[
						59160,
						2,
						0
					],
					[
						59280,
						3,
						120
					]
				],
				"mustHitSection": true
			},
			{
				"gfSection": true,
				"lengthInSteps": 16,
				"sectionNotes": [
					[
						59520,
						1,
						120
					],
					[
						59760,
						0,
						0
					],
					[
						59880,
						1,
						0
					],
					[
						60000,
						3,
						0
					],
					[
						60120,
						1,
						0
					],
					[
						60240,
						2,
						0
					],
					[
						60360,
						0,
						0
					],
					[
						60480,
						2,
						120
					],
					[
						60720,
						3,
						0
					],
					[
						60840,
						2,
						0
					],
					[
						60960,
						3,
						0
					],
					[
						61200,
						0,
						120
					]
				],
				"mustHitSection": true
			},
			{
				"lengthInSteps": 16,
				"sectionNotes": [
					[
						61440,
						1,
						120
					],
					[
						61680,
						0,
						120
					],
					[
						61680,
						2,
						120
					],
					[
						61920,
						3,
						120
					],
					[
						62160,
						0,
						120
					],
					[
						62160,
						2,
						120
					],
					[
						62400,
						1,
						120
					],
					[
						62640,
						3,
						0
					],
					[
						62880,
						1,
						360
					]
				],
				"mustHitSection": false
			},
			{
				"lengthInSteps": 16,
				"sectionNotes": [
					[
						63600,
						2,
						120,
						"Enemyextra1"
					],
					[
						63360,
						3,
						120,
						"Enemyextra1"
					],
					[
						63600,
						0,
						120,
						"Enemyextra1"
					],
					[
						63840,
						3,
						120,
						"Enemyextra1"
					],
					[
						64080,
						2,
						120,
						"Enemyextra1"
					],
					[
						64080,
						0,
						120,
						"Enemyextra1"
					],
					[
						64560,
						0,
						0,
						"Enemyextra1"
					],
					[
						64320,
						1,
						60,
						"Enemyextra1"
					],
					[
						64800,
						1,
						360,
						"Enemyextra1"
					]
				],
				"mustHitSection": false
			},
			{
				"gfSection": true,
				"lengthInSteps": 16,
				"sectionNotes": [
					[
						65280,
						2,
						120
					],
					[
						65520,
						1,
						120
					],
					[
						65520,
						3,
						120
					],
					[
						65760,
						2,
						120
					],
					[
						66000,
						1,
						120
					],
					[
						66000,
						3,
						120
					],
					[
						66240,
						2,
						120
					],
					[
						66480,
						0,
						0
					],
					[
						66720,
						2,
						360
					]
				],
				"mustHitSection": true
			},
			{
				"lengthInSteps": 16,
				"sectionNotes": [
					[
						67440,
						0,
						120
					],
					[
						67200,
						3,
						120
					],
					[
						67440,
						1,
						120
					],
					[
						67680,
						2,
						120
					],
					[
						67920,
						1,
						120
					],
					[
						67920,
						3,
						120
					],
					[
						68400,
						0,
						0
					],
					[
						68160,
						2,
						60
					],
					[
						68640,
						2,
						360
					]
				],
				"mustHitSection": true
			},
			{
				"lengthInSteps": 16,
				"sectionNotes": [
					[
						69120,
						1,
						0
					],
					[
						69180,
						0,
						0
					],
					[
						69240,
						2,
						0
					],
					[
						69300,
						1,
						0
					],
					[
						69360,
						3,
						0
					],
					[
						69420,
						2,
						0
					],
					[
						69480,
						0,
						0
					],
					[
						69540,
						1,
						0
					],
					[
						69600,
						3,
						0
					],
					[
						69660,
						2,
						0
					],
					[
						69720,
						0,
						0
					],
					[
						69780,
						1,
						0
					],
					[
						69840,
						3,
						0
					],
					[
						69900,
						2,
						0
					],
					[
						69960,
						0,
						0
					],
					[
						70020,
						1,
						0
					],
					[
						70080,
						3,
						0
					],
					[
						70140,
						2,
						0
					],
					[
						70200,
						0,
						0
					],
					[
						70260,
						1,
						0
					],
					[
						70320,
						3,
						0
					],
					[
						70380,
						2,
						0
					],
					[
						70440,
						0,
						0
					],
					[
						70500,
						2,
						0
					],
					[
						70560,
						3,
						0
					],
					[
						70620,
						2,
						0
					],
					[
						70680,
						0,
						0
					],
					[
						70740,
						1,
						0
					],
					[
						70800,
						3,
						0
					],
					[
						70860,
						2,
						0
					],
					[
						70920,
						0,
						0
					],
					[
						70980,
						1,
						0
					]
				],
				"mustHitSection": true
			},
			{
				"lengthInSteps": 16,
				"sectionNotes": [
					[
						71040,
						3,
						0
					],
					[
						71100,
						2,
						0
					],
					[
						71160,
						0,
						0
					],
					[
						71220,
						1,
						0
					],
					[
						71280,
						3,
						0
					],
					[
						71340,
						2,
						0
					],
					[
						71400,
						0,
						0
					],
					[
						71460,
						1,
						0
					],
					[
						71520,
						3,
						0
					],
					[
						71580,
						2,
						60
					],
					[
						71760,
						0,
						0
					],
					[
						71880,
						2,
						0
					],
					[
						72000,
						1,
						0
					],
					[
						72120,
						3,
						0
					],
					[
						72240,
						1,
						0
					],
					[
						72360,
						3,
						0
					],
					[
						72480,
						2,
						0
					],
					[
						72600,
						0,
						0
					],
					[
						72720,
						1,
						60
					]
				],
				"mustHitSection": true
			},
			{
				"lengthInSteps": 16,
				"sectionNotes": [
					[
						72960,
						1,
						0,
						"Enemyextra1"
					],
					[
						73020,
						0,
						0,
						"Enemyextra1"
					],
					[
						73080,
						2,
						0,
						"Enemyextra1"
					],
					[
						73140,
						1,
						0,
						"Enemyextra1"
					],
					[
						73200,
						3,
						0,
						"Enemyextra1"
					],
					[
						73260,
						1,
						0,
						"Enemyextra1"
					],
					[
						73320,
						2,
						0,
						"Enemyextra1"
					],
					[
						73380,
						0,
						0,
						"Enemyextra1"
					],
					[
						73440,
						1,
						0,
						"Enemyextra1"
					],
					[
						73500,
						3,
						0,
						"Enemyextra1"
					],
					[
						73560,
						1,
						0,
						"Enemyextra1"
					],
					[
						73620,
						2,
						0,
						"Enemyextra1"
					],
					[
						73680,
						0,
						0,
						"Enemyextra1"
					],
					[
						73740,
						1,
						0,
						"Enemyextra1"
					],
					[
						73800,
						3,
						0,
						"Enemyextra1"
					],
					[
						73860,
						2,
						0,
						"Enemyextra1"
					],
					[
						73920,
						0,
						0,
						"Enemyextra1"
					],
					[
						73980,
						2,
						0,
						"Enemyextra1"
					],
					[
						74040,
						1,
						0,
						"Enemyextra1"
					],
					[
						74100,
						3,
						0,
						"Enemyextra1"
					],
					[
						74160,
						1,
						0,
						"Enemyextra1"
					],
					[
						74220,
						0,
						0,
						"Enemyextra1"
					],
					[
						74280,
						1,
						0,
						"Enemyextra1"
					],
					[
						74340,
						3,
						0,
						"Enemyextra1"
					],
					[
						74400,
						2,
						0,
						"Enemyextra1"
					],
					[
						74460,
						0,
						0,
						"Enemyextra1"
					],
					[
						74520,
						1,
						0,
						"Enemyextra1"
					],
					[
						74580,
						3,
						0,
						"Enemyextra1"
					],
					[
						74640,
						2,
						0,
						"Enemyextra1"
					],
					[
						74700,
						0,
						0,
						"Enemyextra1"
					],
					[
						74760,
						1,
						0,
						"Enemyextra1"
					],
					[
						74820,
						3,
						0,
						"Enemyextra1"
					]
				],
				"mustHitSection": false
			},
			{
				"lengthInSteps": 16,
				"sectionNotes": [
					[
						74880,
						2,
						0,
						"Enemyextra1"
					],
					[
						74940,
						0,
						0,
						"Enemyextra1"
					],
					[
						75000,
						3,
						0,
						"Enemyextra1"
					],
					[
						75060,
						1,
						0,
						"Enemyextra1"
					],
					[
						75160,
						3,
						0,
						"Enemyextra1"
					],
					[
						75240,
						1,
						0,
						"Enemyextra1"
					],
					[
						75300,
						0,
						0,
						"Enemyextra1"
					],
					[
						75360,
						2,
						0,
						"Enemyextra1"
					],
					[
						75420,
						1,
						0,
						"Enemyextra1"
					],
					[
						75480,
						3,
						0,
						"Enemyextra1"
					],
					[
						75600,
						1,
						0,
						"Enemyextra1"
					],
					[
						75720,
						2,
						0,
						"Enemyextra1"
					],
					[
						75840,
						0,
						0,
						"Enemyextra1"
					],
					[
						75960,
						1,
						0,
						"Enemyextra1"
					],
					[
						76080,
						0,
						0,
						"Enemyextra1"
					],
					[
						76200,
						1,
						0,
						"Enemyextra1"
					],
					[
						76320,
						3,
						0,
						"Enemyextra1"
					],
					[
						76440,
						2,
						0,
						"Enemyextra1"
					],
					[
						76560,
						0,
						60,
						"Enemyextra1"
					]
				],
				"mustHitSection": false
			},
			{
				"lengthInSteps": 16,
				"sectionNotes": [
					[
						76800,
						1,
						0
					],
					[
						76860,
						0,
						0
					],
					[
						76920,
						2,
						0
					],
					[
						76980,
						1,
						0
					],
					[
						77040,
						3,
						0
					],
					[
						77100,
						2,
						0
					],
					[
						77160,
						0,
						0
					],
					[
						77220,
						1,
						0
					],
					[
						77280,
						3,
						0
					],
					[
						77340,
						1,
						0
					],
					[
						77400,
						2,
						0
					],
					[
						77460,
						0,
						0
					],
					[
						77520,
						1,
						0
					],
					[
						77580,
						3,
						0
					],
					[
						77640,
						1,
						0
					],
					[
						77700,
						0,
						0
					],
					[
						77760,
						2,
						0
					],
					[
						77820,
						3,
						0
					],
					[
						77940,
						0,
						0
					],
					[
						77880,
						2,
						0
					],
					[
						78000,
						2,
						0
					],
					[
						78060,
						3,
						0
					],
					[
						78120,
						2,
						0
					],
					[
						78180,
						0,
						0
					],
					[
						78240,
						2,
						0
					],
					[
						78300,
						3,
						0
					],
					[
						78360,
						1,
						0
					],
					[
						78420,
						0,
						0
					],
					[
						78480,
						2,
						0
					],
					[
						78540,
						1,
						0
					],
					[
						78600,
						3,
						0
					],
					[
						78660,
						0,
						0
					]
				],
				"mustHitSection": false
			},
			{
				"lengthInSteps": 16,
				"sectionNotes": [
					[
						78720,
						2,
						0
					],
					[
						78780,
						3,
						0
					],
					[
						78840,
						1,
						0
					],
					[
						78900,
						0,
						0
					],
					[
						78960,
						2,
						0
					],
					[
						79020,
						1,
						0
					],
					[
						79080,
						3,
						0
					],
					[
						79140,
						2,
						0
					],
					[
						79200,
						0,
						0
					],
					[
						79260,
						1,
						0
					],
					[
						79320,
						3,
						0
					],
					[
						79380,
						1,
						0
					],
					[
						79440,
						0,
						0
					],
					[
						79560,
						2,
						0
					],
					[
						79680,
						1,
						0
					],
					[
						79800,
						0,
						0
					],
					[
						79920,
						1,
						0
					],
					[
						80040,
						0,
						0
					],
					[
						80160,
						1,
						0
					],
					[
						80280,
						3,
						0
					],
					[
						80400,
						1,
						0
					],
					[
						80400,
						0,
						60
					]
				],
				"mustHitSection": false
			},
			{
				"gfSection": true,
				"lengthInSteps": 16,
				"sectionNotes": [
					[
						80640,
						1,
						0
					],
					[
						80700,
						3,
						0
					],
					[
						80820,
						0,
						0
					],
					[
						80760,
						2,
						0
					],
					[
						80880,
						1,
						0
					],
					[
						80940,
						3,
						0
					],
					[
						81000,
						2,
						0
					],
					[
						81060,
						0,
						0
					],
					[
						81120,
						1,
						0
					],
					[
						81180,
						3,
						0
					],
					[
						81240,
						2,
						0
					],
					[
						81300,
						0,
						0
					],
					[
						81360,
						1,
						0
					],
					[
						81420,
						3,
						0
					],
					[
						81480,
						2,
						0
					],
					[
						81600,
						0,
						0
					],
					[
						81660,
						1,
						0
					],
					[
						81720,
						3,
						0
					],
					[
						81780,
						2,
						0
					],
					[
						81840,
						0,
						0
					],
					[
						81900,
						2,
						0
					],
					[
						81960,
						3,
						0
					],
					[
						82020,
						2,
						0
					],
					[
						82080,
						0,
						0
					],
					[
						82140,
						2,
						0
					],
					[
						82200,
						1,
						0
					],
					[
						82260,
						3,
						0
					],
					[
						82320,
						2,
						0
					],
					[
						82380,
						0,
						0
					],
					[
						82440,
						1,
						0
					],
					[
						82500,
						3,
						0
					]
				],
				"mustHitSection": true
			},
			{
				"gfSection": true,
				"lengthInSteps": 16,
				"sectionNotes": [
					[
						82560,
						2,
						0
					],
					[
						82620,
						0,
						0
					],
					[
						82680,
						2,
						0
					],
					[
						82740,
						1,
						0
					],
					[
						82800,
						3,
						0
					],
					[
						82860,
						1,
						0
					],
					[
						82920,
						2,
						0
					],
					[
						82980,
						0,
						0
					],
					[
						83040,
						1,
						0
					],
					[
						83100,
						3,
						0
					],
					[
						83160,
						2,
						0
					],
					[
						83280,
						0,
						0
					],
					[
						83400,
						2,
						0
					],
					[
						83520,
						1,
						0
					],
					[
						83640,
						3,
						0
					],
					[
						83760,
						1,
						0
					],
					[
						83880,
						3,
						0
					],
					[
						84000,
						0,
						0
					],
					[
						84120,
						2,
						0
					],
					[
						84240,
						1,
						120
					]
				],
				"mustHitSection": true
			},
			{
				"lengthInSteps": 16,
				"sectionNotes": [
					[
						84480,
						1,
						120
					],
					[
						84840,
						3,
						0
					],
					[
						84960,
						1,
						120
					],
					[
						85200,
						0,
						60
					],
					[
						85680,
						2,
						0
					],
					[
						85920,
						1,
						360
					]
				],
				"mustHitSection": false
			},
			{
				"lengthInSteps": 16,
				"sectionNotes": [
					[
						86640,
						1,
						120,
						"Enemyextra1"
					],
					[
						86880,
						0,
						0,
						"Enemyextra1"
					],
					[
						87120,
						1,
						120,
						"Enemyextra1"
					],
					[
						87360,
						3,
						120,
						"Enemyextra1"
					],
					[
						87600,
						2,
						0,
						"Enemyextra1"
					],
					[
						87840,
						1,
						360,
						"Enemyextra1"
					]
				],
				"mustHitSection": false
			},
			{
				"gfSection": true,
				"lengthInSteps": 16,
				"sectionNotes": [
					[
						88320,
						1,
						360
					],
					[
						88800,
						3,
						0
					],
					[
						89040,
						3,
						0
					],
					[
						89640,
						2,
						0
					],
					[
						89520,
						0,
						0
					],
					[
						89760,
						1,
						300
					]
				],
				"mustHitSection": true
			},
			{
				"lengthInSteps": 16,
				"sectionNotes": [
					[
						90240,
						2,
						120
					],
					[
						90480,
						1,
						0
					],
					[
						90720,
						3,
						120
					],
					[
						91200,
						1,
						120
					],
					[
						90960,
						0,
						0
					],
					[
						91440,
						2,
						0
					],
					[
						91680,
						3,
						120
					],
					[
						91920,
						1,
						0
					]
				],
				"mustHitSection": true
			},
			{
				"lengthInSteps": 16,
				"sectionNotes": [
					[
						92160,
						0,
						120
					],
					[
						92520,
						1,
						0
					],
					[
						92640,
						3,
						120
					],
					[
						92880,
						1,
						0
					],
					[
						93360,
						1,
						0
					],
					[
						93600,
						2,
						360
					]
				],
				"mustHitSection": true
			},
			{
				"gfSection": true,
				"lengthInSteps": 16,
				"sectionNotes": [
					[
						94320,
						2,
						120
					],
					[
						94560,
						1,
						0
					],
					[
						94800,
						3,
						120
					],
					[
						95040,
						1,
						120
					],
					[
						95280,
						0,
						0
					],
					[
						95520,
						2,
						360
					]
				],
				"mustHitSection": true
			},
			{
				"lengthInSteps": 16,
				"sectionNotes": [
					[
						96000,
						1,
						360,
						"Enemyextra1"
					],
					[
						96480,
						3,
						0,
						"Enemyextra1"
					],
					[
						96720,
						1,
						0,
						"Enemyextra1"
					],
					[
						97200,
						0,
						0,
						"Enemyextra1"
					],
					[
						97320,
						2,
						0,
						"Enemyextra1"
					],
					[
						97440,
						1,
						300,
						"Enemyextra1"
					]
				],
				"mustHitSection": false
			},
			{
				"lengthInSteps": 16,
				"sectionNotes": [
					[
						97920,
						2,
						120
					],
					[
						98160,
						0,
						0
					],
					[
						98400,
						2,
						120
					],
					[
						98640,
						1,
						0
					],
					[
						98880,
						3,
						120
					],
					[
						99120,
						1,
						0
					],
					[
						99360,
						2,
						120
					],
					[
						99600,
						0,
						0
					]
				],
				"mustHitSection": false
			},
			{
				"lengthInSteps": 16,
				"sectionNotes": [
					[
						100800,
						1,
						120,
						"Enemyextra1"
					],
					[
						101520,
						1,
						120,
						"Enemyextra1"
					],
					[
						101160,
						0,
						240,
						"Enemyextra1"
					],
					[
						100800,
						6,
						840,
						"GF Sing"
					],
					[
						100800,
						7,
						840
					]
				],
				"mustHitSection": false
			},
			{
				"lengthInSteps": 16,
				"sectionNotes": [
					[
						101760,
						2,
						60
					],
					[
						102120,
						3,
						60
					],
					[
						102480,
						0,
						60
					],
					[
						102720,
						1,
						360
					],
					[
						102720,
						3,
						360,
						"Enemyextra1"
					]
				],
				"mustHitSection": false
			},
			{
				"lengthInSteps": 16,
				"sectionNotes": [],
				"mustHitSection": false
			},
			{
				"lengthInSteps": 16,
				"sectionNotes": [],
				"mustHitSection": false
			},
			{
				"lengthInSteps": 16,
				"sectionNotes": [],
				"mustHitSection": false
			},
			{
				"lengthInSteps": 16,
				"sectionNotes": [],
				"mustHitSection": false
			},
			{
				"lengthInSteps": 16,
				"sectionNotes": [],
				"mustHitSection": false
			},
			{
				"lengthInSteps": 16,
				"sectionNotes": [],
				"mustHitSection": false
			},
			{
				"lengthInSteps": 16,
				"sectionNotes": [],
				"mustHitSection": false
			},
			{
				"lengthInSteps": 16,
				"sectionNotes": [],
				"mustHitSection": false
			},
			{
				"lengthInSteps": 16,
				"sectionNotes": [],
				"mustHitSection": false
			},
			{
				"lengthInSteps": 16,
				"sectionNotes": [],
				"mustHitSection": false
			},
			{
				"lengthInSteps": 16,
				"sectionNotes": [],
				"mustHitSection": false
			},
			{
				"sectionBeats": 4,
				"sectionNotes": [],
				"typeOfSection": 0,
				"gfSection": false,
				"altAnim": false,
				"mustHitSection": false,
				"changeBPM": false,
				"bpm": 180
			},
			{
				"typeOfSection": 0,
				"sectionNotes": [],
				"sectionBeats": 4,
				"altAnim": false,
				"gfSection": false,
				"bpm": 200,
				"changeBPM": false,
				"mustHitSection": false
			},
			{
				"sectionBeats": 4,
				"sectionNotes": [],
				"typeOfSection": 0,
				"gfSection": false,
				"altAnim": false,
				"mustHitSection": false,
				"changeBPM": false,
				"bpm": 200
			},
			{
				"sectionBeats": 4,
				"sectionNotes": [],
				"typeOfSection": 0,
				"gfSection": false,
				"altAnim": false,
				"mustHitSection": true,
				"changeBPM": false,
				"bpm": 120
			},
			{
				"sectionBeats": 4,
				"sectionNotes": [],
				"typeOfSection": 0,
				"gfSection": false,
				"altAnim": false,
				"mustHitSection": true,
				"changeBPM": false,
				"bpm": 120
			},
			{
				"sectionBeats": 4,
				"sectionNotes": [],
				"typeOfSection": 0,
				"gfSection": false,
				"altAnim": false,
				"mustHitSection": true,
				"changeBPM": false,
				"bpm": 120
			},
			{
				"sectionBeats": 4,
				"sectionNotes": [],
				"typeOfSection": 0,
				"gfSection": false,
				"altAnim": false,
				"mustHitSection": true,
				"changeBPM": false,
				"bpm": 120
			},
			{
				"sectionBeats": 4,
				"sectionNotes": [],
				"typeOfSection": 0,
				"gfSection": false,
				"altAnim": false,
				"mustHitSection": false,
				"changeBPM": false,
				"bpm": 120
			},
			{
				"typeOfSection": 0,
				"sectionNotes": [],
				"sectionBeats": 4,
				"altAnim": false,
				"gfSection": false,
				"bpm": 120,
				"changeBPM": false,
				"mustHitSection": false
			},
			{
				"sectionBeats": 4,
				"sectionNotes": [],
				"typeOfSection": 0,
				"gfSection": false,
				"altAnim": false,
				"mustHitSection": false,
				"changeBPM": false,
				"bpm": 120
			},
			{
				"sectionBeats": 4,
				"sectionNotes": [],
				"typeOfSection": 0,
				"gfSection": false,
				"altAnim": false,
				"mustHitSection": false,
				"changeBPM": false,
				"bpm": 120
			},
			{
				"sectionBeats": 4,
				"sectionNotes": [],
				"typeOfSection": 0,
				"gfSection": false,
				"altAnim": false,
				"mustHitSection": true,
				"changeBPM": false,
				"bpm": 120
			},
			{
				"sectionBeats": 4,
				"sectionNotes": [],
				"typeOfSection": 0,
				"gfSection": false,
				"altAnim": false,
				"mustHitSection": true,
				"changeBPM": false,
				"bpm": 120
			},
			{
				"sectionBeats": 4,
				"sectionNotes": [],
				"typeOfSection": 0,
				"gfSection": false,
				"altAnim": false,
				"mustHitSection": true,
				"changeBPM": false,
				"bpm": 120
			},
			{
				"sectionBeats": 4,
				"sectionNotes": [],
				"typeOfSection": 0,
				"gfSection": false,
				"altAnim": false,
				"mustHitSection": true,
				"changeBPM": false,
				"bpm": 120
			},
			{
				"sectionBeats": 4,
				"sectionNotes": [],
				"typeOfSection": 0,
				"gfSection": false,
				"altAnim": false,
				"mustHitSection": true,
				"changeBPM": false,
				"bpm": 120
			},
			{
				"sectionBeats": 4,
				"sectionNotes": [],
				"typeOfSection": 0,
				"gfSection": false,
				"altAnim": false,
				"mustHitSection": true,
				"changeBPM": false,
				"bpm": 120
			},
			{
				"sectionBeats": 4,
				"sectionNotes": [],
				"typeOfSection": 0,
				"gfSection": false,
				"altAnim": false,
				"mustHitSection": false,
				"changeBPM": false,
				"bpm": 120
			},
			{
				"sectionBeats": 4,
				"sectionNotes": [],
				"typeOfSection": 0,
				"gfSection": false,
				"altAnim": false,
				"mustHitSection": false,
				"changeBPM": false,
				"bpm": 120
			},
			{
				"sectionBeats": 4,
				"sectionNotes": [],
				"typeOfSection": 0,
				"gfSection": false,
				"altAnim": false,
				"mustHitSection": false,
				"changeBPM": false,
				"bpm": 120
			},
			{
				"sectionBeats": 4,
				"sectionNotes": [],
				"typeOfSection": 0,
				"gfSection": false,
				"altAnim": false,
				"mustHitSection": true,
				"changeBPM": false,
				"bpm": 120
			},
			{
				"sectionBeats": 4,
				"sectionNotes": [],
				"typeOfSection": 0,
				"gfSection": false,
				"altAnim": false,
				"mustHitSection": true,
				"changeBPM": false,
				"bpm": 120
			},
			{
				"sectionBeats": 4,
				"sectionNotes": [],
				"typeOfSection": 0,
				"gfSection": false,
				"altAnim": false,
				"mustHitSection": true,
				"changeBPM": false,
				"bpm": 120
			},
			{
				"sectionBeats": 4,
				"sectionNotes": [],
				"typeOfSection": 0,
				"gfSection": false,
				"altAnim": false,
				"mustHitSection": true,
				"changeBPM": false,
				"bpm": 120
			},
			{
				"sectionBeats": 4,
				"sectionNotes": [],
				"typeOfSection": 0,
				"gfSection": false,
				"altAnim": false,
				"mustHitSection": false,
				"changeBPM": false,
				"bpm": 120
			},
			{
				"sectionBeats": 4,
				"sectionNotes": [],
				"typeOfSection": 0,
				"gfSection": false,
				"altAnim": false,
				"mustHitSection": false,
				"changeBPM": false,
				"bpm": 120
			},
			{
				"sectionBeats": 4,
				"sectionNotes": [],
				"typeOfSection": 0,
				"gfSection": false,
				"altAnim": false,
				"mustHitSection": false,
				"changeBPM": false,
				"bpm": 120
			},
			{
				"sectionBeats": 4,
				"sectionNotes": [],
				"typeOfSection": 0,
				"gfSection": false,
				"altAnim": false,
				"mustHitSection": false,
				"changeBPM": false,
				"bpm": 120
			},
			{
				"sectionBeats": 4,
				"sectionNotes": [],
				"typeOfSection": 0,
				"gfSection": false,
				"altAnim": false,
				"mustHitSection": true,
				"changeBPM": false,
				"bpm": 120
			},
			{
				"sectionBeats": 4,
				"sectionNotes": [],
				"typeOfSection": 0,
				"gfSection": false,
				"altAnim": false,
				"mustHitSection": true,
				"changeBPM": false,
				"bpm": 120
			},
			{
				"sectionBeats": 4,
				"sectionNotes": [],
				"typeOfSection": 0,
				"gfSection": false,
				"altAnim": false,
				"mustHitSection": true,
				"changeBPM": false,
				"bpm": 120
			},
			{
				"sectionBeats": 4,
				"sectionNotes": [],
				"typeOfSection": 0,
				"gfSection": false,
				"altAnim": false,
				"mustHitSection": true,
				"changeBPM": false,
				"bpm": 120
			},
			{
				"sectionBeats": 4,
				"sectionNotes": [],
				"typeOfSection": 0,
				"gfSection": false,
				"altAnim": false,
				"mustHitSection": true,
				"changeBPM": false,
				"bpm": 120
			},
			{
				"sectionBeats": 4,
				"sectionNotes": [],
				"typeOfSection": 0,
				"gfSection": false,
				"altAnim": false,
				"mustHitSection": false,
				"changeBPM": false,
				"bpm": 120
			},
			{
				"sectionBeats": 4,
				"sectionNotes": [],
				"typeOfSection": 0,
				"gfSection": false,
				"altAnim": false,
				"mustHitSection": true,
				"changeBPM": false,
				"bpm": 120
			},
			{
				"sectionBeats": 4,
				"sectionNotes": [],
				"typeOfSection": 0,
				"gfSection": false,
				"altAnim": false,
				"mustHitSection": true,
				"changeBPM": false,
				"bpm": 120
			},
			{
				"sectionBeats": 4,
				"sectionNotes": [],
				"typeOfSection": 0,
				"gfSection": false,
				"altAnim": false,
				"mustHitSection": true,
				"changeBPM": false,
				"bpm": 120
			},
			{
				"sectionBeats": 4,
				"sectionNotes": [],
				"typeOfSection": 0,
				"gfSection": false,
				"altAnim": false,
				"mustHitSection": true,
				"changeBPM": false,
				"bpm": 120
			},
			{
				"typeOfSection": 0,
				"sectionNotes": [],
				"sectionBeats": 4,
				"altAnim": false,
				"gfSection": false,
				"bpm": 120,
				"changeBPM": false,
				"mustHitSection": true
			},
			{
				"typeOfSection": 0,
				"sectionNotes": [],
				"sectionBeats": 4,
				"altAnim": false,
				"gfSection": false,
				"bpm": 200,
				"changeBPM": false,
				"mustHitSection": true
			},
			{
				"typeOfSection": 0,
				"sectionNotes": [],
				"sectionBeats": 4,
				"altAnim": false,
				"gfSection": false,
				"bpm": 200,
				"changeBPM": false,
				"mustHitSection": true
			},
			{
				"typeOfSection": 0,
				"sectionNotes": [],
				"sectionBeats": 4,
				"altAnim": false,
				"gfSection": false,
				"bpm": 200,
				"changeBPM": false,
				"mustHitSection": true
			},
			{
				"sectionBeats": 4,
				"sectionNotes": [],
				"typeOfSection": 0,
				"gfSection": false,
				"altAnim": false,
				"mustHitSection": true,
				"changeBPM": false,
				"bpm": 200
			},
			{
				"sectionBeats": 4,
				"sectionNotes": [],
				"typeOfSection": 0,
				"gfSection": false,
				"altAnim": false,
				"mustHitSection": true,
				"changeBPM": false,
				"bpm": 200
			},
			{
				"sectionBeats": 4,
				"sectionNotes": [],
				"typeOfSection": 0,
				"gfSection": false,
				"altAnim": false,
				"mustHitSection": true,
				"changeBPM": false,
				"bpm": 200
			},
			{
				"typeOfSection": 0,
				"sectionNotes": [],
				"sectionBeats": 4,
				"altAnim": false,
				"gfSection": false,
				"bpm": 200,
				"changeBPM": false,
				"mustHitSection": true
			},
			{
				"typeOfSection": 0,
				"sectionNotes": [],
				"sectionBeats": 4,
				"altAnim": false,
				"gfSection": false,
				"bpm": 200,
				"changeBPM": false,
				"mustHitSection": true
			},
			{
				"typeOfSection": 0,
				"sectionNotes": [],
				"sectionBeats": 4,
				"altAnim": false,
				"gfSection": false,
				"bpm": 200,
				"changeBPM": false,
				"mustHitSection": true
			},
			{
				"sectionBeats": 4,
				"sectionNotes": [],
				"typeOfSection": 0,
				"gfSection": false,
				"altAnim": false,
				"mustHitSection": true,
				"changeBPM": false,
				"bpm": 200
			},
			{
				"sectionBeats": 4,
				"sectionNotes": [],
				"typeOfSection": 0,
				"gfSection": false,
				"altAnim": false,
				"mustHitSection": true,
				"changeBPM": false,
				"bpm": 200
			},
			{
				"sectionBeats": 4,
				"sectionNotes": [],
				"typeOfSection": 0,
				"gfSection": false,
				"altAnim": false,
				"mustHitSection": true,
				"changeBPM": false,
				"bpm": 200
			},
			{
				"typeOfSection": 0,
				"sectionNotes": [],
				"sectionBeats": 4,
				"altAnim": false,
				"gfSection": false,
				"bpm": 200,
				"changeBPM": false,
				"mustHitSection": true
			},
			{
				"typeOfSection": 0,
				"sectionNotes": [],
				"sectionBeats": 4,
				"altAnim": false,
				"gfSection": false,
				"bpm": 200,
				"changeBPM": false,
				"mustHitSection": true
			},
			{
				"typeOfSection": 0,
				"sectionNotes": [],
				"sectionBeats": 4,
				"altAnim": false,
				"gfSection": false,
				"bpm": 200,
				"changeBPM": false,
				"mustHitSection": true
			},
			{
				"typeOfSection": 0,
				"sectionNotes": [],
				"sectionBeats": 4,
				"altAnim": false,
				"gfSection": false,
				"bpm": 200,
				"changeBPM": false,
				"mustHitSection": true
			},
			{
				"typeOfSection": 0,
				"sectionNotes": [],
				"sectionBeats": 4,
				"altAnim": false,
				"gfSection": false,
				"bpm": 200,
				"changeBPM": false,
				"mustHitSection": true
			},
			{
				"sectionBeats": 4,
				"sectionNotes": [],
				"typeOfSection": 0,
				"gfSection": false,
				"altAnim": false,
				"mustHitSection": true,
				"changeBPM": false,
				"bpm": 200
			},
			{
				"sectionBeats": 4,
				"sectionNotes": [],
				"typeOfSection": 0,
				"gfSection": false,
				"altAnim": false,
				"mustHitSection": true,
				"changeBPM": false,
				"bpm": 200
			},
			{
				"sectionBeats": 4,
				"sectionNotes": [],
				"typeOfSection": 0,
				"gfSection": false,
				"altAnim": false,
				"mustHitSection": true,
				"changeBPM": false,
				"bpm": 200
			},
			{
				"sectionBeats": 4,
				"sectionNotes": [],
				"typeOfSection": 0,
				"gfSection": false,
				"altAnim": false,
				"mustHitSection": true,
				"changeBPM": false,
				"bpm": 200
			},
			{
				"sectionBeats": 4,
				"sectionNotes": [],
				"typeOfSection": 0,
				"gfSection": false,
				"altAnim": false,
				"mustHitSection": true,
				"changeBPM": false,
				"bpm": 200
			},
			{
				"sectionBeats": 4,
				"sectionNotes": [],
				"typeOfSection": 0,
				"gfSection": false,
				"altAnim": false,
				"mustHitSection": true,
				"changeBPM": false,
				"bpm": 200
			},
			{
				"sectionBeats": 4,
				"sectionNotes": [],
				"typeOfSection": 0,
				"gfSection": false,
				"altAnim": false,
				"mustHitSection": true,
				"changeBPM": false,
				"bpm": 200
			}
		],
		"gfVersion": "lucasta-left ALT",
		"events": [],
		"player3": null,
		"song": "WarZ",
		"validScore": true,
		"needsVoices": true,
		"stage": "leftBG",
		"speed": 3,
		"bpm": 125
	}
}