{
	"animations": [
		{
			"loop": false,
			"offsets": [
				75,
				-10
			],
			"anim": "singLEFT",
			"fps": 24,
			"name": "Right",
			"indices": []
		},
		{
			"loop": false,
			"offsets": [
				18,
				-66
			],
			"anim": "singDOWN",
			"fps": 24,
			"name": "Down",
			"indices": []
		},
		{
			"loop": false,
			"offsets": [
				-61,
				17
			],
			"anim": "singUP",
			"fps": 24,
			"name": "Up",
			"indices": []
		},
		{
			"loop": false,
			"offsets": [
				-29,
				-24
			],
			"anim": "singRIGHT",
			"fps": 24,
			"name": "Left",
			"indices": []
		},
		{
			"offsets": [
				0,
				0
			],
			"indices": [],
			"fps": 20,
			"anim": "idle",
			"loop": false,
			"name": "Idle"
		}
	],
	"no_antialiasing": false,
	"image": "characters/AquinoPato",
	"position": [
		100,
		250
	],
	"healthicon": "aquino_pato_icon",
	"flip_x": true,
	"healthbar_colors": [
		102,
		51,
		51
	],
	"camera_position": [
		0,
		0
	],
	"sing_duration": 3.5,
	"scale": 0.9,
	"_editor_isPlayer": false
}