{
	"song": {
		"player1": "gf_discord",
		"gfVersion": "neko-cuadradito",
		"notes": [
			{
				"sectionBeats": 4,
				"sectionNotes": [],
				"typeOfSection": 0,
				"gfSection": false,
				"altAnim": false,
				"mustHitSection": true,
				"changeBPM": false,
				"bpm": 150
			},
			{
				"sectionBeats": 4,
				"sectionNotes": [
					[
						2638.88888888889,
						1,
						0
					],
					[
						2222.22222222222,
						3,
						139
					],
					[
						2916.66666666667,
						3,
						139
					],
					[
						3333.33333333333,
						3,
						0
					],
					[
						3611.11111111111,
						3,
						139
					],
					[
						3888.88888888889,
						2,
						0
					],
					[
						4166.66666666667,
						2,
						139
					]
				],
				"typeOfSection": 0,
				"gfSection": false,
				"altAnim": false,
				"mustHitSection": false,
				"changeBPM": false,
				"bpm": 150
			},
			{
				"sectionBeats": 4,
				"sectionNotes": [
					[
						4444.44444444444,
						1,
						0
					],
					[
						4722.22222222222,
						3,
						0
					],
					[
						4861.11111111111,
						1,
						0
					],
					[
						5034.72222222222,
						0,
						0
					],
					[
						5138.88888888889,
						3,
						0
					],
					[
						5416.66666666667,
						1,
						0
					],
					[
						5694.44444444444,
						0,
						0
					],
					[
						5833.33333333333,
						2,
						0
					],
					[
						6111.11111111111,
						3,
						0
					],
					[
						6250,
						0,
						0
					],
					[
						6388.88888888889,
						2,
						139
					]
				],
				"typeOfSection": 0,
				"gfSection": false,
				"altAnim": false,
				"mustHitSection": false,
				"changeBPM": false,
				"bpm": 150
			},
			{
				"sectionBeats": 4,
				"sectionNotes": [
					[
						6805.55555555555,
						3,
						0
					],
					[
						7500,
						2,
						0
					],
					[
						7638.88888888889,
						3,
						0
					],
					[
						7222.22222222222,
						3,
						0
					],
					[
						8333.33333333333,
						0,
						139
					],
					[
						8611.11111111111,
						3,
						139
					],
					[
						7777.77777777778,
						1,
						208.333333333333
					]
				],
				"typeOfSection": 0,
				"gfSection": false,
				"altAnim": false,
				"mustHitSection": false,
				"changeBPM": false,
				"bpm": 150
			},
			{
				"sectionBeats": 4,
				"sectionNotes": [
					[
						8888.88888888889,
						1,
						0
					],
					[
						9166.66666666667,
						1,
						0
					],
					[
						9305.55555555555,
						3,
						0
					],
					[
						9722.22222222222,
						0,
						139
					],
					[
						10000,
						1,
						0
					],
					[
						10277.7777777778,
						2,
						0
					],
					[
						10416.6666666667,
						1,
						0
					],
					[
						10694.4444444444,
						1,
						0
					],
					[
						9444.44444444444,
						2,
						0
					],
					[
						10833.3333333333,
						3,
						138.888888888889
					]
				],
				"typeOfSection": 0,
				"gfSection": false,
				"altAnim": false,
				"mustHitSection": false,
				"changeBPM": false,
				"bpm": 150
			},
			{
				"sectionBeats": 4,
				"sectionNotes": [
					[
						11111.1111111111,
						3,
						139
					],
					[
						11805.5555555556,
						3,
						139
					],
					[
						12083.3333333333,
						2,
						0
					],
					[
						12222.2222222222,
						3,
						0
					],
					[
						12500,
						3,
						139
					],
					[
						12777.7777777778,
						2,
						0
					],
					[
						13055.5555555556,
						2,
						139
					],
					[
						11527.7777777778,
						1,
						0
					]
				],
				"typeOfSection": 0,
				"gfSection": false,
				"altAnim": false,
				"mustHitSection": true,
				"changeBPM": false,
				"bpm": 150
			},
			{
				"sectionBeats": 4,
				"sectionNotes": [
					[
						13333.3333333333,
						1,
						0
					],
					[
						13611.1111111111,
						3,
						0
					],
					[
						13750,
						1,
						0
					],
					[
						14166.6666666667,
						1,
						0
					],
					[
						14444.4444444444,
						2,
						0
					],
					[
						14583.3333333333,
						0,
						0
					],
					[
						14861.1111111111,
						2,
						0
					],
					[
						15138.8888888889,
						0,
						0
					],
					[
						15277.7777777778,
						2,
						139
					],
					[
						13888.8888888889,
						2,
						0
					]
				],
				"typeOfSection": 0,
				"gfSection": false,
				"altAnim": false,
				"mustHitSection": true,
				"changeBPM": false,
				"bpm": 150
			},
			{
				"sectionBeats": 4,
				"sectionNotes": [
					[
						15694.4444444444,
						3,
						0
					],
					[
						16388.8888888889,
						2,
						0
					],
					[
						16527.7777777778,
						3,
						0
					],
					[
						16666.6666666667,
						1,
						139
					],
					[
						17083.3333333333,
						2,
						0
					],
					[
						17222.2222222222,
						0,
						139
					],
					[
						17500,
						3,
						139
					],
					[
						16111.1111111111,
						3,
						0
					]
				],
				"typeOfSection": 0,
				"gfSection": false,
				"altAnim": false,
				"mustHitSection": true,
				"changeBPM": false,
				"bpm": 150
			},
			{
				"sectionBeats": 4,
				"sectionNotes": [
					[
						17777.7777777778,
						1,
						0
					],
					[
						18055.5555555556,
						1,
						0
					],
					[
						18472.2222222222,
						3,
						0
					],
					[
						18611.1111111111,
						0,
						139
					],
					[
						18888.8888888889,
						1,
						0
					],
					[
						19166.6666666667,
						2,
						0
					],
					[
						19756.9444444444,
						3,
						0
					],
					[
						19861.1111111111,
						0,
						0
					],
					[
						18333.3333333333,
						2,
						0
					],
					[
						19444.4444444444,
						1,
						0
					]
				],
				"typeOfSection": 0,
				"gfSection": false,
				"altAnim": false,
				"mustHitSection": true,
				"changeBPM": false,
				"bpm": 150
			},
			{
				"sectionBeats": 4,
				"sectionNotes": [
					[
						20000,
						3,
						0
					],
					[
						20555.5555555556,
						2,
						0
					],
					[
						20833.3333333333,
						2,
						139
					],
					[
						21111.1111111111,
						1,
						0
					],
					[
						21388.8888888889,
						1,
						0
					],
					[
						21666.6666666667,
						2,
						0
					],
					[
						21944.4444444444,
						2,
						139
					],
					[
						21111.1111111111,
						4,
						417
					],
					[
						20000,
						7,
						417
					],
					[
						20138.8888888889,
						1,
						0
					],
					[
						20277.7777777778,
						0,
						0
					]
				],
				"typeOfSection": 0,
				"gfSection": false,
				"altAnim": false,
				"mustHitSection": false,
				"changeBPM": false,
				"bpm": 150
			},
			{
				"sectionBeats": 4,
				"sectionNotes": [
					[
						22222.2222222222,
						0,
						0
					],
					[
						22430.5555555556,
						2,
						0
					],
					[
						22500,
						3,
						0
					],
					[
						22638.8888888889,
						0,
						0
					],
					[
						22777.7777777778,
						2,
						0
					],
					[
						23055.5555555556,
						0,
						139
					],
					[
						23333.3333333333,
						3,
						0
					],
					[
						23611.1111111111,
						3,
						0
					],
					[
						23750,
						2,
						0
					],
					[
						24027.7777777778,
						3,
						0
					],
					[
						23333.3333333333,
						4,
						417
					],
					[
						22222.2222222222,
						7,
						417
					],
					[
						24166.6666666667,
						1,
						138.888888888889
					]
				],
				"typeOfSection": 0,
				"gfSection": false,
				"altAnim": false,
				"mustHitSection": false,
				"changeBPM": false,
				"bpm": 150
			},
			{
				"sectionBeats": 4,
				"sectionNotes": [
					[
						24444.4444444444,
						6,
						417
					],
					[
						25555.5555555556,
						7,
						417
					],
					[
						24444.4444444444,
						2,
						139
					],
					[
						24722.2222222222,
						1,
						0
					],
					[
						25277.7777777778,
						1,
						0
					],
					[
						25000,
						0,
						139
					],
					[
						25555.5555555556,
						3,
						0
					],
					[
						25833.3333333333,
						3,
						139
					],
					[
						26111.1111111111,
						2,
						417
					]
				],
				"typeOfSection": 0,
				"gfSection": false,
				"altAnim": false,
				"mustHitSection": false,
				"changeBPM": false,
				"bpm": 150
			},
			{
				"sectionBeats": 4,
				"sectionNotes": [
					[
						26666.6666666667,
						6,
						417
					],
					[
						27777.7777777778,
						5,
						417
					],
					[
						28333.3333333333,
						4,
						417
					],
					[
						26666.6666666667,
						0,
						139
					],
					[
						27222.2222222222,
						1,
						139
					],
					[
						27500,
						2,
						139
					],
					[
						27777.7777777778,
						0,
						139
					],
					[
						28055.5555555556,
						1,
						139
					],
					[
						28333.3333333333,
						2,
						417
					],
					[
						26944.4444444444,
						3,
						138.888888888889
					]
				],
				"typeOfSection": 0,
				"gfSection": false,
				"altAnim": false,
				"mustHitSection": false,
				"changeBPM": false,
				"bpm": 150
			},
			{
				"sectionBeats": 4,
				"sectionNotes": [
					[
						28888.8888888889,
						3,
						0
					],
					[
						29027.7777777778,
						1,
						0
					],
					[
						29166.6666666667,
						2,
						0
					],
					[
						29583.3333333333,
						3,
						0
					],
					[
						29722.2222222222,
						2,
						139
					],
					[
						30555.5555555556,
						2,
						0
					],
					[
						30833.3333333333,
						2,
						139
					],
					[
						30000,
						4,
						417
					],
					[
						28888.8888888889,
						7,
						417
					],
					[
						29444.4444444444,
						0,
						0
					],
					[
						30000,
						3,
						0
					],
					[
						30277.7777777778,
						3,
						0
					]
				],
				"typeOfSection": 0,
				"gfSection": false,
				"altAnim": false,
				"mustHitSection": true,
				"changeBPM": false,
				"bpm": 150
			},
			{
				"sectionBeats": 4,
				"sectionNotes": [
					[
						31111.1111111111,
						0,
						0
					],
					[
						31319.4444444444,
						2,
						0
					],
					[
						31527.7777777778,
						0,
						0
					],
					[
						31666.6666666667,
						2,
						0
					],
					[
						31944.4444444444,
						0,
						139
					],
					[
						32222.2222222222,
						3,
						0
					],
					[
						32500,
						3,
						0
					],
					[
						32777.7777777778,
						1,
						0
					],
					[
						32916.6666666667,
						3,
						0
					],
					[
						32222.2222222222,
						4,
						417
					],
					[
						31111.1111111111,
						7,
						417
					],
					[
						31805.5555555556,
						3,
						0
					],
					[
						33055.5555555556,
						1,
						138.888888888889
					]
				],
				"typeOfSection": 0,
				"gfSection": false,
				"altAnim": false,
				"mustHitSection": true,
				"changeBPM": false,
				"bpm": 150
			},
			{
				"sectionBeats": 4,
				"sectionNotes": [
					[
						33333.3333333333,
						6,
						417
					],
					[
						34444.4444444444,
						7,
						417
					],
					[
						34444.4444444444,
						3,
						0
					],
					[
						34722.2222222222,
						3,
						139
					],
					[
						35000,
						2,
						417
					],
					[
						33333.3333333333,
						2,
						208.333333333333
					],
					[
						33888.8888888889,
						0,
						208.333333333333
					]
				],
				"typeOfSection": 0,
				"gfSection": false,
				"altAnim": false,
				"mustHitSection": true,
				"changeBPM": false,
				"bpm": 150
			},
			{
				"sectionBeats": 4,
				"sectionNotes": [
					[
						35555.5555555556,
						6,
						417
					],
					[
						36666.6666666667,
						5,
						417
					],
					[
						37222.2222222222,
						4,
						417
					],
					[
						35555.5555555556,
						0,
						139
					],
					[
						36111.1111111111,
						1,
						139
					],
					[
						36388.8888888889,
						2,
						139
					],
					[
						36666.6666666667,
						0,
						139
					],
					[
						36944.4444444444,
						1,
						139
					],
					[
						37222.2222222222,
						2,
						417
					],
					[
						35833.3333333333,
						3,
						138.888888888889
					]
				],
				"typeOfSection": 0,
				"gfSection": false,
				"altAnim": false,
				"mustHitSection": true,
				"changeBPM": false,
				"bpm": 150
			},
			{
				"sectionBeats": 4,
				"sectionNotes": [
					[
						39166.6666666667,
						3,
						0
					],
					[
						39444.4444444444,
						3,
						417
					],
					[
						37777.7777777778,
						0,
						416.666666666667
					],
					[
						38333.3333333333,
						1,
						277.777777777778
					]
				],
				"typeOfSection": 0,
				"gfSection": false,
				"altAnim": false,
				"mustHitSection": true,
				"changeBPM": false,
				"bpm": 150
			},
			{
				"sectionBeats": 4,
				"sectionNotes": [
					[
						41111.1111111111,
						2,
						139
					],
					[
						41388.8888888889,
						1,
						139
					],
					[
						41666.6666666667,
						3,
						139
					],
					[
						41944.4444444444,
						1,
						139
					],
					[
						40000,
						2,
						416.666666666667
					],
					[
						40555.5555555555,
						1,
						416.666666666667
					]
				],
				"typeOfSection": 0,
				"gfSection": false,
				"altAnim": false,
				"mustHitSection": true,
				"changeBPM": false,
				"bpm": 150
			},
			{
				"sectionBeats": 4,
				"sectionNotes": [
					[
						42222.2222222222,
						2,
						417
					],
					[
						42777.7777777778,
						1,
						417
					],
					[
						43333.3333333333,
						3,
						417
					],
					[
						43888.8888888889,
						0,
						417
					]
				],
				"typeOfSection": 0,
				"gfSection": false,
				"altAnim": false,
				"mustHitSection": true,
				"changeBPM": false,
				"bpm": 150
			},
			{
				"sectionBeats": 4,
				"sectionNotes": [
					[
						44444.4444444444,
						2,
						417
					],
					[
						45000,
						1,
						417
					],
					[
						46111.1111111111,
						0,
						417
					],
					[
						45555.5555555555,
						2,
						417
					]
				],
				"typeOfSection": 0,
				"gfSection": false,
				"altAnim": false,
				"mustHitSection": true,
				"changeBPM": false,
				"bpm": 150
			},
			{
				"sectionBeats": 4,
				"sectionNotes": [
					[
						48055.5555555556,
						3,
						0
					],
					[
						48333.3333333333,
						3,
						417
					],
					[
						46666.6666666666,
						7,
						973
					],
					[
						46666.6666666666,
						0,
						208.333333333333
					],
					[
						47222.2222222222,
						3,
						208.333333333333
					]
				],
				"typeOfSection": 0,
				"gfSection": false,
				"altAnim": false,
				"mustHitSection": false,
				"changeBPM": false,
				"bpm": 150
			},
			{
				"sectionBeats": 4,
				"sectionNotes": [
					[
						50000,
						2,
						139
					],
					[
						50277.7777777778,
						1,
						139
					],
					[
						50555.5555555555,
						3,
						139
					],
					[
						50833.3333333333,
						1,
						139
					],
					[
						48888.8888888889,
						2,
						208.333333333333
					],
					[
						49444.4444444444,
						1,
						208.333333333333
					]
				],
				"typeOfSection": 0,
				"gfSection": false,
				"altAnim": false,
				"mustHitSection": false,
				"changeBPM": false,
				"bpm": 150
			},
			{
				"sectionBeats": 4,
				"sectionNotes": [
					[
						51111.1111111111,
						2,
						417
					],
					[
						51666.6666666667,
						1,
						417
					],
					[
						52222.2222222222,
						3,
						417
					],
					[
						52777.7777777778,
						0,
						417
					]
				],
				"typeOfSection": 0,
				"gfSection": false,
				"altAnim": false,
				"mustHitSection": false,
				"changeBPM": false,
				"bpm": 150
			},
			{
				"sectionBeats": 4,
				"sectionNotes": [
					[
						53333.3333333333,
						2,
						417
					],
					[
						53888.8888888889,
						1,
						417
					],
					[
						55000,
						0,
						417
					],
					[
						54444.4444444444,
						2,
						417
					]
				],
				"typeOfSection": 0,
				"gfSection": false,
				"altAnim": false,
				"mustHitSection": false,
				"changeBPM": false,
				"bpm": 150
			},
			{
				"sectionBeats": 4,
				"sectionNotes": [
					[
						55555.5555555555,
						0,
						139
					],
					[
						56111.1111111111,
						0,
						139
					],
					[
						55555.5555555555,
						7,
						973
					],
					[
						56666.6666666666,
						0,
						0
					],
					[
						56805.5555555555,
						2,
						0
					],
					[
						57083.3333333333,
						2,
						139
					],
					[
						57500,
						0,
						139
					]
				],
				"typeOfSection": 0,
				"gfSection": false,
				"altAnim": false,
				"mustHitSection": true,
				"changeBPM": false,
				"bpm": 150
			},
			{
				"sectionBeats": 4,
				"sectionNotes": [
					[
						58055.5555555555,
						0,
						0
					],
					[
						58333.3333333333,
						0,
						139
					],
					[
						59027.7777777777,
						2,
						0
					],
					[
						59166.6666666666,
						1,
						0
					],
					[
						59305.5555555555,
						2,
						139
					],
					[
						59722.2222222222,
						0,
						139
					],
					[
						58611.1111111111,
						3,
						0
					],
					[
						58888.8888888889,
						3,
						0
					]
				],
				"typeOfSection": 0,
				"gfSection": false,
				"altAnim": false,
				"mustHitSection": true,
				"changeBPM": false,
				"bpm": 150
			},
			{
				"sectionBeats": 4,
				"sectionNotes": [
					[
						60000,
						2,
						0
					],
					[
						60277.7777777777,
						3,
						0
					],
					[
						60833.3333333333,
						2,
						0
					],
					[
						62013.8888888889,
						0,
						0
					],
					[
						60416.6666666666,
						2,
						0
					],
					[
						60694.4444444444,
						1,
						0
					],
					[
						60972.2222222222,
						3,
						0
					],
					[
						61250,
						2,
						0
					],
					[
						61527.7777777777,
						0,
						0
					],
					[
						61666.6666666666,
						2,
						0
					],
					[
						61944.4444444444,
						1,
						0
					]
				],
				"typeOfSection": 0,
				"gfSection": false,
				"altAnim": false,
				"mustHitSection": true,
				"changeBPM": false,
				"bpm": 150
			},
			{
				"sectionBeats": 4,
				"sectionNotes": [
					[
						62222.2222222222,
						2,
						0
					],
					[
						62361.1111111111,
						1,
						0
					],
					[
						62500,
						3,
						0
					],
					[
						62777.7777777777,
						3,
						0
					],
					[
						62916.6666666666,
						2,
						0
					],
					[
						63333.3333333333,
						3,
						0
					],
					[
						63611.1111111111,
						2,
						0
					],
					[
						64166.6666666666,
						0,
						139
					],
					[
						63055.5555555555,
						0,
						0
					],
					[
						63888.8888888888,
						3,
						0
					]
				],
				"typeOfSection": 0,
				"gfSection": false,
				"altAnim": false,
				"mustHitSection": true,
				"changeBPM": false,
				"bpm": 150
			},
			{
				"sectionBeats": 4,
				"sectionNotes": [
					[
						64444.4444444444,
						0,
						139
					],
					[
						65000,
						0,
						139
					],
					[
						65555.5555555555,
						0,
						0
					],
					[
						65694.4444444444,
						2,
						0
					],
					[
						65833.3333333333,
						1,
						0
					],
					[
						65972.2222222222,
						2,
						139
					],
					[
						66388.8888888889,
						0,
						139
					]
				],
				"typeOfSection": 0,
				"gfSection": false,
				"altAnim": false,
				"mustHitSection": false,
				"changeBPM": false,
				"bpm": 150
			},
			{
				"sectionBeats": 4,
				"sectionNotes": [
					[
						66944.4444444444,
						0,
						0
					],
					[
						67222.2222222222,
						0,
						139
					],
					[
						67916.6666666666,
						2,
						0
					],
					[
						68055.5555555555,
						1,
						0
					],
					[
						68194.4444444444,
						2,
						139
					],
					[
						68611.1111111111,
						0,
						139
					],
					[
						67500,
						3,
						0
					],
					[
						67777.7777777777,
						3,
						0
					]
				],
				"typeOfSection": 0,
				"gfSection": false,
				"altAnim": false,
				"mustHitSection": false,
				"changeBPM": false,
				"bpm": 150
			},
			{
				"sectionBeats": 4,
				"sectionNotes": [
					[
						70694.4444444444,
						3,
						0
					],
					[
						70833.3333333333,
						2,
						0
					],
					[
						70902.7777777777,
						0,
						0
					],
					[
						71041.6666666666,
						0,
						0
					],
					[
						68888.8888888888,
						2,
						0
					],
					[
						69166.6666666666,
						1,
						0
					],
					[
						69305.5555555555,
						3,
						0
					],
					[
						69444.4444444444,
						2,
						0
					],
					[
						69722.2222222222,
						1,
						0
					],
					[
						69861.1111111111,
						3,
						0
					],
					[
						70000,
						1,
						0
					],
					[
						70277.7777777777,
						2,
						0
					],
					[
						70555.5555555555,
						0,
						0
					]
				],
				"typeOfSection": 0,
				"gfSection": false,
				"altAnim": false,
				"mustHitSection": false,
				"changeBPM": false,
				"bpm": 150
			},
			{
				"sectionBeats": 4,
				"sectionNotes": [
					[
						71111.1111111111,
						2,
						0
					],
					[
						71250,
						1,
						0
					],
					[
						71388.8888888888,
						3,
						0
					],
					[
						71666.6666666666,
						3,
						0
					],
					[
						71805.5555555555,
						2,
						0
					],
					[
						71944.4444444444,
						0,
						0
					],
					[
						72222.2222222222,
						3,
						0
					],
					[
						72500,
						2,
						0
					],
					[
						72777.7777777777,
						0,
						139
					],
					[
						73055.5555555555,
						0,
						139
					]
				],
				"typeOfSection": 0,
				"gfSection": false,
				"altAnim": false,
				"mustHitSection": false,
				"changeBPM": false,
				"bpm": 150
			},
			{
				"sectionBeats": 4,
				"sectionNotes": [
					[
						73333.3333333333,
						0,
						0
					],
					[
						73888.8888888888,
						3,
						0
					],
					[
						74444.4444444444,
						0,
						0
					],
					[
						74722.2222222222,
						3,
						0
					],
					[
						75000,
						2,
						0
					],
					[
						75277.7777777777,
						1,
						0
					]
				],
				"typeOfSection": 0,
				"gfSection": false,
				"altAnim": false,
				"mustHitSection": true,
				"changeBPM": false,
				"bpm": 150
			},
			{
				"sectionBeats": 4,
				"sectionNotes": [
					[
						75555.5555555555,
						0,
						0
					],
					[
						76111.1111111111,
						3,
						0
					],
					[
						76666.6666666666,
						0,
						0
					],
					[
						77222.2222222222,
						2,
						0
					],
					[
						76944.4444444444,
						0,
						0
					],
					[
						77499.9999999999,
						0,
						0
					]
				],
				"typeOfSection": 0,
				"gfSection": false,
				"altAnim": false,
				"mustHitSection": false,
				"changeBPM": false,
				"bpm": 150
			},
			{
				"sectionBeats": 4,
				"sectionNotes": [
					[
						77777.7777777777,
						2,
						0
					],
					[
						78333.3333333333,
						1,
						0
					],
					[
						78888.8888888888,
						2,
						0
					],
					[
						79166.6666666666,
						2,
						0
					],
					[
						79444.4444444444,
						0,
						0
					],
					[
						79722.2222222222,
						3,
						0
					]
				],
				"typeOfSection": 0,
				"gfSection": false,
				"altAnim": false,
				"mustHitSection": true,
				"changeBPM": false,
				"bpm": 150
			},
			{
				"sectionBeats": 4,
				"sectionNotes": [
					[
						79999.9999999999,
						2,
						0
					],
					[
						80555.5555555555,
						1,
						0
					],
					[
						81111.1111111111,
						2,
						0
					],
					[
						81666.6666666666,
						0,
						0
					],
					[
						81944.4444444444,
						3,
						0
					],
					[
						81388.8888888888,
						3,
						0
					]
				],
				"typeOfSection": 0,
				"gfSection": false,
				"altAnim": false,
				"mustHitSection": false,
				"changeBPM": false,
				"bpm": 150
			},
			{
				"sectionBeats": 4,
				"sectionNotes": [
					[
						82222.2222222222,
						1,
						0
					],
					[
						82777.7777777777,
						1,
						0
					],
					[
						83333.3333333333,
						1,
						0
					],
					[
						83611.1111111111,
						2,
						0
					],
					[
						83888.8888888888,
						0,
						0
					],
					[
						84166.6666666666,
						1,
						0
					]
				],
				"typeOfSection": 0,
				"gfSection": false,
				"altAnim": false,
				"mustHitSection": false,
				"changeBPM": false,
				"bpm": 150
			},
			{
				"sectionBeats": 4,
				"sectionNotes": [
					[
						84444.4444444444,
						1,
						0
					],
					[
						85555.5555555555,
						1,
						0
					],
					[
						85833.3333333333,
						2,
						0
					],
					[
						86111.1111111111,
						0,
						0
					],
					[
						86388.8888888888,
						2,
						0
					],
					[
						84999.9999999999,
						3,
						0
					]
				],
				"typeOfSection": 0,
				"gfSection": false,
				"altAnim": false,
				"mustHitSection": true,
				"changeBPM": false,
				"bpm": 150
			},
			{
				"sectionBeats": 4,
				"sectionNotes": [
					[
						86666.6666666666,
						2,
						0
					],
					[
						86944.4444444444,
						1,
						0
					],
					[
						87222.2222222222,
						0,
						0
					],
					[
						87499.9999999999,
						2,
						0
					],
					[
						87777.7777777777,
						1,
						0
					],
					[
						88055.5555555555,
						0,
						0
					],
					[
						88333.3333333333,
						1,
						417
					]
				],
				"typeOfSection": 0,
				"gfSection": false,
				"altAnim": false,
				"mustHitSection": false,
				"changeBPM": false,
				"bpm": 150
			},
			{
				"sectionBeats": 4,
				"sectionNotes": [
					[
						88888.8888888888,
						2,
						0
					],
					[
						89444.4444444444,
						0,
						0
					],
					[
						89166.6666666666,
						3,
						0
					],
					[
						89722.2222222221,
						3,
						0
					],
					[
						89999.9999999999,
						2,
						0
					],
					[
						90277.7777777777,
						3,
						0
					],
					[
						90555.5555555555,
						0,
						417
					]
				],
				"typeOfSection": 0,
				"gfSection": false,
				"altAnim": false,
				"mustHitSection": true,
				"changeBPM": false,
				"bpm": 150
			},
			{
				"sectionBeats": 4,
				"sectionNotes": [
					[
						91666.6666666667,
						0,
						0
					],
					[
						91111.1111111111,
						3,
						139
					],
					[
						91805.5555555556,
						3,
						139
					],
					[
						92083.3333333333,
						2,
						0
					],
					[
						92222.2222222222,
						3,
						0
					],
					[
						92500,
						3,
						139
					],
					[
						92777.7777777778,
						2,
						0
					],
					[
						93055.5555555556,
						2,
						139
					]
				],
				"typeOfSection": 0,
				"gfSection": false,
				"altAnim": false,
				"mustHitSection": false,
				"changeBPM": false,
				"bpm": 150
			},
			{
				"sectionBeats": 4,
				"sectionNotes": [
					[
						93333.3333333333,
						1,
						0
					],
					[
						93611.1111111111,
						3,
						0
					],
					[
						93750,
						1,
						0
					],
					[
						94444.4444444445,
						2,
						0
					],
					[
						94583.3333333333,
						0,
						0
					],
					[
						95000,
						3,
						0
					],
					[
						95138.8888888889,
						0,
						0
					],
					[
						95277.7777777778,
						2,
						139
					],
					[
						94027.7777777777,
						2,
						0
					],
					[
						94166.6666666666,
						0,
						0
					],
					[
						94722.2222222221,
						3,
						0
					]
				],
				"typeOfSection": 0,
				"gfSection": false,
				"altAnim": false,
				"mustHitSection": false,
				"changeBPM": false,
				"bpm": 150
			},
			{
				"sectionBeats": 4,
				"sectionNotes": [
					[
						95694.4444444444,
						3,
						0
					],
					[
						96388.8888888889,
						2,
						0
					],
					[
						96527.7777777778,
						3,
						0
					],
					[
						96111.1111111111,
						3,
						0
					],
					[
						96666.6666666667,
						1,
						139
					],
					[
						97083.3333333333,
						2,
						0
					],
					[
						97222.2222222222,
						0,
						139
					],
					[
						97500,
						3,
						139
					]
				],
				"typeOfSection": 0,
				"gfSection": false,
				"altAnim": false,
				"mustHitSection": false,
				"changeBPM": false,
				"bpm": 150
			},
			{
				"sectionBeats": 4,
				"sectionNotes": [
					[
						97777.7777777778,
						1,
						0
					],
					[
						98055.5555555556,
						1,
						0
					],
					[
						98194.4444444444,
						3,
						0
					],
					[
						98472.2222222222,
						3,
						0
					],
					[
						98611.1111111111,
						0,
						139
					],
					[
						99027.7777777778,
						0,
						0
					],
					[
						99166.6666666667,
						2,
						0
					],
					[
						99305.5555555556,
						1,
						0
					],
					[
						99756.9444444444,
						3,
						139
					],
					[
						98333.3333333333,
						2,
						0
					],
					[
						98888.8888888888,
						2,
						0
					],
					[
						99444.4444444444,
						3,
						0
					]
				],
				"typeOfSection": 0,
				"gfSection": false,
				"altAnim": false,
				"mustHitSection": false,
				"changeBPM": false,
				"bpm": 150
			},
			{
				"sectionBeats": 4,
				"sectionNotes": [
					[
						100416.666666667,
						1,
						0
					],
					[
						100000,
						3,
						139
					],
					[
						100694.444444444,
						3,
						139
					],
					[
						100972.222222222,
						2,
						0
					],
					[
						101111.111111111,
						3,
						0
					],
					[
						101388.888888889,
						3,
						139
					],
					[
						101666.666666667,
						2,
						0
					],
					[
						101944.444444444,
						2,
						139
					]
				],
				"typeOfSection": 0,
				"gfSection": false,
				"altAnim": false,
				"mustHitSection": true,
				"changeBPM": false,
				"bpm": 150
			},
			{
				"sectionBeats": 4,
				"sectionNotes": [
					[
						102222.222222222,
						1,
						0
					],
					[
						102361.111111111,
						0,
						0
					],
					[
						102916.666666667,
						3,
						0
					],
					[
						103333.333333333,
						2,
						0
					],
					[
						103472.222222222,
						0,
						0
					],
					[
						104027.777777778,
						0,
						0
					],
					[
						104166.666666667,
						2,
						139
					],
					[
						102500,
						2,
						0
					],
					[
						102777.777777778,
						1,
						0
					],
					[
						103055.555555555,
						0,
						0
					],
					[
						103611.111111111,
						3,
						0
					],
					[
						103750,
						1,
						0
					]
				],
				"typeOfSection": 0,
				"gfSection": false,
				"altAnim": false,
				"mustHitSection": true,
				"changeBPM": false,
				"bpm": 150
			},
			{
				"sectionBeats": 4,
				"sectionNotes": [
					[
						104583.333333333,
						3,
						0
					],
					[
						104861.111111111,
						3,
						0
					],
					[
						105277.777777778,
						2,
						0
					],
					[
						105416.666666667,
						3,
						0
					],
					[
						105000,
						3,
						0
					],
					[
						105555.555555556,
						1,
						139
					],
					[
						105972.222222222,
						2,
						0
					],
					[
						106111.111111111,
						0,
						139
					],
					[
						106388.888888889,
						3,
						139
					]
				],
				"typeOfSection": 0,
				"gfSection": false,
				"altAnim": false,
				"mustHitSection": true,
				"changeBPM": false,
				"bpm": 150
			},
			{
				"sectionBeats": 4,
				"sectionNotes": [
					[
						106666.666666667,
						1,
						0
					],
					[
						106944.444444444,
						1,
						0
					],
					[
						107083.333333333,
						3,
						0
					],
					[
						107222.222222222,
						1,
						0
					],
					[
						107361.111111111,
						3,
						0
					],
					[
						107500,
						0,
						139
					],
					[
						107916.666666667,
						0,
						0
					],
					[
						108055.555555556,
						2,
						0
					],
					[
						108194.444444444,
						1,
						0
					],
					[
						108333.333333333,
						3,
						0
					],
					[
						108472.222222222,
						1,
						0
					],
					[
						108750,
						0,
						0
					],
					[
						107777.777777778,
						2,
						0
					],
					[
						108611.111111111,
						2,
						0
					]
				],
				"typeOfSection": 0,
				"gfSection": false,
				"altAnim": false,
				"mustHitSection": true,
				"changeBPM": false,
				"bpm": 150
			},
			{
				"sectionBeats": 4,
				"sectionNotes": [
					[
						108888.888888889,
						3,
						0
					],
					[
						109722.222222222,
						2,
						139
					],
					[
						110000,
						1,
						0
					],
					[
						110138.888888889,
						3,
						0
					],
					[
						110277.777777778,
						1,
						0
					],
					[
						110416.666666667,
						3,
						0
					],
					[
						110694.444444444,
						3,
						0
					],
					[
						110833.333333333,
						2,
						139
					],
					[
						110000,
						4,
						417
					],
					[
						108888.888888889,
						7,
						417
					],
					[
						109027.777777778,
						1,
						0
					],
					[
						109305.555555555,
						2,
						0
					],
					[
						109583.333333333,
						0,
						0
					]
				],
				"typeOfSection": 0,
				"gfSection": false,
				"altAnim": false,
				"mustHitSection": false,
				"changeBPM": false,
				"bpm": 150
			},
			{
				"sectionBeats": 4,
				"sectionNotes": [
					[
						111111.111111111,
						0,
						0
					],
					[
						111805.555555556,
						0,
						0
					],
					[
						111944.444444444,
						0,
						139
					],
					[
						112222.222222222,
						3,
						0
					],
					[
						112361.111111111,
						1,
						0
					],
					[
						112638.888888889,
						2,
						0
					],
					[
						112777.777777778,
						1,
						0
					],
					[
						112916.666666667,
						3,
						0
					],
					[
						112222.222222222,
						4,
						417
					],
					[
						111111.111111111,
						7,
						417
					],
					[
						111250,
						2,
						0
					],
					[
						111527.777777778,
						1,
						0
					],
					[
						113055.555555555,
						0,
						138.888888888889
					]
				],
				"typeOfSection": 0,
				"gfSection": false,
				"altAnim": false,
				"mustHitSection": false,
				"changeBPM": false,
				"bpm": 150
			},
			{
				"sectionBeats": 4,
				"sectionNotes": [
					[
						113333.333333333,
						6,
						417
					],
					[
						114444.444444444,
						7,
						417
					],
					[
						113333.333333333,
						2,
						139
					],
					[
						113611.111111111,
						1,
						0
					],
					[
						114166.666666667,
						1,
						0
					],
					[
						113888.888888889,
						0,
						139
					],
					[
						114444.444444444,
						3,
						0
					],
					[
						114722.222222222,
						3,
						139
					],
					[
						115000,
						2,
						417
					]
				],
				"typeOfSection": 0,
				"gfSection": false,
				"altAnim": false,
				"mustHitSection": false,
				"changeBPM": false,
				"bpm": 150
			},
			{
				"sectionBeats": 4,
				"sectionNotes": [
					[
						115555.555555556,
						6,
						417
					],
					[
						116666.666666667,
						5,
						417
					],
					[
						117222.222222222,
						4,
						417
					],
					[
						115555.555555556,
						0,
						139
					],
					[
						116111.111111111,
						1,
						139
					],
					[
						116388.888888889,
						2,
						139
					],
					[
						116666.666666667,
						0,
						139
					],
					[
						116944.444444444,
						1,
						139
					],
					[
						117222.222222222,
						2,
						417
					],
					[
						115833.333333333,
						3,
						138.888888888889
					]
				],
				"typeOfSection": 0,
				"gfSection": false,
				"altAnim": false,
				"mustHitSection": false,
				"changeBPM": false,
				"bpm": 150
			},
			{
				"sectionBeats": 4,
				"sectionNotes": [
					[
						117777.777777778,
						3,
						0
					],
					[
						118611.111111111,
						2,
						139
					],
					[
						118888.888888889,
						1,
						0
					],
					[
						119166.666666667,
						1,
						0
					],
					[
						119305.555555556,
						3,
						0
					],
					[
						119444.444444444,
						2,
						0
					],
					[
						119722.222222222,
						2,
						139
					],
					[
						118888.888888889,
						4,
						417
					],
					[
						117777.777777778,
						7,
						417
					],
					[
						117916.666666667,
						1,
						0
					],
					[
						118194.444444444,
						2,
						0
					],
					[
						118472.222222222,
						0,
						0
					]
				],
				"typeOfSection": 0,
				"gfSection": false,
				"altAnim": false,
				"mustHitSection": true,
				"changeBPM": false,
				"bpm": 150
			},
			{
				"sectionBeats": 4,
				"sectionNotes": [
					[
						120000,
						0,
						0
					],
					[
						120833.333333333,
						0,
						139
					],
					[
						121111.111111111,
						3,
						0
					],
					[
						121250,
						1,
						0
					],
					[
						121388.888888889,
						3,
						0
					],
					[
						121666.666666667,
						1,
						0
					],
					[
						121805.555555556,
						3,
						0
					],
					[
						121111.111111111,
						4,
						417
					],
					[
						120000,
						7,
						417
					],
					[
						120138.888888889,
						2,
						0
					],
					[
						120416.666666667,
						1,
						0
					],
					[
						120694.444444444,
						3,
						0
					],
					[
						121944.444444444,
						0,
						138.888888888889
					]
				],
				"typeOfSection": 0,
				"gfSection": false,
				"altAnim": false,
				"mustHitSection": true,
				"changeBPM": false,
				"bpm": 150
			},
			{
				"sectionBeats": 4,
				"sectionNotes": [
					[
						122222.222222222,
						6,
						417
					],
					[
						123333.333333333,
						7,
						417
					],
					[
						122222.222222222,
						2,
						139
					],
					[
						122500,
						1,
						0
					],
					[
						123055.555555556,
						1,
						0
					],
					[
						122777.777777778,
						0,
						139
					],
					[
						123333.333333333,
						3,
						0
					],
					[
						123611.111111111,
						3,
						139
					],
					[
						123888.888888889,
						2,
						417
					]
				],
				"typeOfSection": 0,
				"gfSection": false,
				"altAnim": false,
				"mustHitSection": true,
				"changeBPM": false,
				"bpm": 150
			},
			{
				"sectionBeats": 4,
				"sectionNotes": [
					[
						124444.444444444,
						6,
						417
					],
					[
						125555.555555556,
						5,
						417
					],
					[
						126111.111111111,
						4,
						417
					],
					[
						124444.444444444,
						0,
						139
					],
					[
						125000,
						1,
						139
					],
					[
						125277.777777778,
						2,
						139
					],
					[
						125555.555555556,
						0,
						139
					],
					[
						125833.333333333,
						1,
						139
					],
					[
						126111.111111111,
						2,
						417
					],
					[
						124722.222222222,
						3,
						138.888888888889
					]
				],
				"typeOfSection": 0,
				"gfSection": false,
				"altAnim": false,
				"mustHitSection": true,
				"changeBPM": false,
				"bpm": 150
			},
			{
				"sectionBeats": 4,
				"sectionNotes": [],
				"typeOfSection": 0,
				"gfSection": false,
				"altAnim": false,
				"mustHitSection": true,
				"changeBPM": false,
				"bpm": 150
			},
			{
				"sectionBeats": 4,
				"sectionNotes": [],
				"typeOfSection": 0,
				"gfSection": false,
				"altAnim": false,
				"mustHitSection": true,
				"changeBPM": false,
				"bpm": 150
			},
			{
				"sectionBeats": 4,
				"sectionNotes": [],
				"typeOfSection": 0,
				"gfSection": false,
				"altAnim": false,
				"mustHitSection": true,
				"changeBPM": false,
				"bpm": 150
			},
			{
				"sectionBeats": 4,
				"sectionNotes": [],
				"typeOfSection": 0,
				"gfSection": false,
				"altAnim": false,
				"mustHitSection": true,
				"changeBPM": false,
				"bpm": 150
			},
			{
				"sectionBeats": 4,
				"sectionNotes": [],
				"typeOfSection": 0,
				"gfSection": false,
				"altAnim": false,
				"mustHitSection": true,
				"changeBPM": false,
				"bpm": 150
			},
			{
				"sectionBeats": 4,
				"sectionNotes": [],
				"typeOfSection": 0,
				"gfSection": false,
				"altAnim": false,
				"mustHitSection": true,
				"changeBPM": false,
				"bpm": 150
			},
			{
				"sectionBeats": 4,
				"sectionNotes": [],
				"typeOfSection": 0,
				"gfSection": false,
				"altAnim": false,
				"mustHitSection": true,
				"changeBPM": false,
				"bpm": 150
			},
			{
				"sectionBeats": 4,
				"sectionNotes": [],
				"typeOfSection": 0,
				"gfSection": false,
				"altAnim": false,
				"mustHitSection": true,
				"changeBPM": false,
				"bpm": 150
			},
			{
				"sectionBeats": 4,
				"sectionNotes": [],
				"typeOfSection": 0,
				"gfSection": false,
				"altAnim": false,
				"mustHitSection": true,
				"changeBPM": false,
				"bpm": 150
			},
			{
				"gfSection": false,
				"altAnim": false,
				"typeOfSection": 0,
				"sectionNotes": [],
				"bpm": 108,
				"sectionBeats": 4,
				"changeBPM": false,
				"mustHitSection": true
			}
		],
		"events": [],
		"player2": "soarinng",
		"song": "Beat the GF",
		"validScore": true,
		"needsVoices": true,
		"stage": "discord",
		"speed": 2.8,
		"bpm": 108
	}
}